pyicu_wheels-2.14.dist-info/METADATA
pyicu_wheels-2.14.dist-info/RECORD
pyicu_wheels-2.14.dist-info/WHEEL
pyicu_wheels-2.14.dist-info/licenses/LICENSE.txt
pyicu_wheels.libs/libicudata-dd5148f6.so.76.1
pyicu_wheels.libs/libicui18n-1d4a9287.so.76.1
pyicu_wheels.libs/libicuuc-3d852464.so.76.1
icu/_icu_.cpython-39-powerpc64le-linux-gnu.so
icu/__about__.py
icu/__init__.py
