Metadata-Version: 2.4
Name: pyicu-wheels
Version: 2.14
Summary: Wheels for PyICU
Project-URL: Documentation, https://github.com/Init7/pyicu#readme
Project-URL: Issues, https://github.com/Init7/pyicu/issues
Project-URL: Source, https://github.com/Init7/pyicu
License-Expression: Apache-2.0
License-File: LICENSE.txt
Keywords: i18n,icu,wheel
Classifier: Development Status :: 4 - Beta
Classifier: Programming Language :: Python
Classifier: Programming Language :: Python :: 3.8
Classifier: Programming Language :: Python :: 3.9
Classifier: Programming Language :: Python :: 3.10
Classifier: Programming Language :: Python :: 3.11
Classifier: Programming Language :: Python :: 3.12
Classifier: Programming Language :: Python :: 3.13
Classifier: Programming Language :: Python :: Implementation :: CPython
Classifier: Programming Language :: Python :: Implementation :: PyPy
Classifier: Topic :: Software Development :: Internationalization
Classifier: Topic :: Software Development :: Localization
Requires-Python: >=3.8
